acceptance_tests/__init__.py
acceptance_tests/base.py
acceptance_tests/tests/__init__.py
acceptance_tests/tests/core/__init__.py
acceptance_tests/tests/core/test_plugin.py
acceptance_tests/tests/plugin/__init__.py
opnsense_cli/__init__.py
opnsense_cli/cli.py
opnsense_cli/api/__init__.py
opnsense_cli/api/base.py
opnsense_cli/api/client.py
opnsense_cli/api/core/__init__.py
opnsense_cli/api/core/firmware.py
opnsense_cli/api/core/ipsec.py
opnsense_cli/api/core/routes.py
opnsense_cli/api/core/syslog.py
opnsense_cli/api/core/unbound.py
opnsense_cli/api/plugin/__init__.py
opnsense_cli/api/plugin/apibackup.py
opnsense_cli/api/plugin/firewall.py
opnsense_cli/api/plugin/haproxy.py
opnsense_cli/api/plugin/nodeexporter.py
opnsense_cli/api/plugin/openvpn.py
opnsense_cli/autoloader/__init__.py
opnsense_cli/autoloader/click_command.py
opnsense_cli/callbacks/__init__.py
opnsense_cli/callbacks/click.py
opnsense_cli/commands/__init__.py
opnsense_cli/commands/completion/__init__.py
opnsense_cli/commands/core/__init__.py
opnsense_cli/commands/core/firewall/__init__.py
opnsense_cli/commands/core/firewall/alias.py
opnsense_cli/commands/core/firewall/rule.py
opnsense_cli/commands/core/ipsec/__init__.py
opnsense_cli/commands/core/ipsec/phase1.py
opnsense_cli/commands/core/ipsec/phase2.py
opnsense_cli/commands/core/openvpn/__init__.py
opnsense_cli/commands/core/plugin/__init__.py
opnsense_cli/commands/core/route/__init__.py
opnsense_cli/commands/core/route/gateway.py
opnsense_cli/commands/core/route/static.py
opnsense_cli/commands/core/syslog/__init__.py
opnsense_cli/commands/core/syslog/destination.py
opnsense_cli/commands/core/syslog/stats.py
opnsense_cli/commands/core/unbound/__init__.py
opnsense_cli/commands/core/unbound/alias.py
opnsense_cli/commands/core/unbound/domain.py
opnsense_cli/commands/core/unbound/host.py
opnsense_cli/commands/new/__init__.py
opnsense_cli/commands/new/api.py
opnsense_cli/commands/new/command.py
opnsense_cli/commands/new/puppet.py
opn_cli-1.7.0.dist-info/LICENSE
opn_cli-1.7.0.dist-info/METADATA
opn_cli-1.7.0.dist-info/WHEEL
opn_cli-1.7.0.dist-info/entry_points.txt
opn_cli-1.7.0.dist-info/top_level.txt
opn_cli-1.7.0.dist-info/RECORD
