Metadata-Version: 2.1
Name: opn-cli
Version: 1.7.0
Summary: OPNsense CLI written in python.
Home-page: UNKNOWN
Author: Andreas Stürz IT-Solutions
License: BSD-2-Clause License
Project-URL: Bug Tracker, https://github.com/andeman/opnsense_cli/issues
Project-URL: CI: GitHub Actions Pipelines, https://github.com/andeman/opnsense_cli/actions
Project-URL: Documentation, https://github.com/andeman/opnsense_cli
Project-URL: Source Code, https://github.com/andeman/opnsense_cli
Platform: UNKNOWN
Classifier: Development Status :: 4 - Beta
Classifier: Environment :: Console
Classifier: Intended Audience :: Developers
Classifier: License :: OSI Approved :: BSD License
Classifier: Operating System :: POSIX
Classifier: Operating System :: MacOS
Classifier: Operating System :: Unix
Classifier: Operating System :: Microsoft :: Windows
Classifier: Programming Language :: Python :: 3 :: Only
Classifier: Programming Language :: Python :: 3.7
Classifier: Programming Language :: Python :: 3.8
Classifier: Programming Language :: Python :: 3.9
Classifier: Programming Language :: Python :: 3.10
Classifier: Programming Language :: Python :: 3.11
Classifier: Topic :: Software Development :: Libraries :: Python Modules
Requires-Python: >=3.7
License-File: LICENSE
Requires-Dist: click (>=8.0.1)
Requires-Dist: requests
Requires-Dist: PTable
Requires-Dist: PyYAML
Requires-Dist: jsonpath-ng
Requires-Dist: beautifulsoup4
Requires-Dist: lxml
Requires-Dist: Jinja2
